{
  "head" : {
    "vars" : [ "k", "v" ]
  },
  "results" : {
    "bindings" : [ {
      "k" : {
        "type" : "uri",
        "value" : "http://www.wikidata.org/prop/direct/P1772"
      },
      "v" : {
        "type" : "literal",
        "value" : "PIDE5"
      }
    }, {
      "k" : {
        "type" : "uri",
        "value" : "http://www.wikidata.org/prop/direct/P1843"
      },
      "v" : {
        "xml:lang" : "ko",
        "type" : "literal",
        "value" : "소나무"
      }
    }, {
      "k" : {
        "type" : "uri",
        "value" : "http://www.wikidata.org/prop/direct/P1843"
      },
      "v" : {
        "xml:lang" : "zh",
        "type" : "literal",
        "value" : "赤松"
      }
    }, {
      "k" : {
        "type" : "uri",
        "value" : "http://www.wikidata.org/prop/direct/P1843"
      },
      "v" : {
        "xml:lang" : "de",
        "type" : "literal",
        "value" : "Japanische Rotkiefer"
      }
    }, {
      "k" : {
        "type" : "uri",
        "value" : "http://www.wikidata.org/prop/direct/P1843"
      },
      "v" : {
        "xml:lang" : "en",
        "type" : "literal",
        "value" : "Japanese red pine"
      }
    }, {
      "k" : {
        "type" : "uri",
        "value" : "http://www.wikidata.org/prop/direct/P1843"
      },
      "v" : {
        "xml:lang" : "en",
        "type" : "literal",
        "value" : "Japanese Red Pine"
      }
    }, {
      "k" : {
        "type" : "uri",
        "value" : "http://www.wikidata.org/prop/direct/P1843"
      },
      "v" : {
        "xml:lang" : "fi",
        "type" : "literal",
        "value" : "Japaninpunamänty"
      }
    }, {
      "k" : {
        "type" : "uri",
        "value" : "http://www.wikidata.org/prop/direct/P1843"
      },
      "v" : {
        "xml:lang" : "fr",
        "type" : "literal",
        "value" : "Pin rouge du Japon"
      }
    }, {
      "k" : {
        "type" : "uri",
        "value" : "http://www.wikidata.org/prop/direct/P1843"
      },
      "v" : {
        "xml:lang" : "ja",
        "type" : "literal",
        "value" : "アカマツ（赤松）"
      }
    }, {
      "k" : {
        "type" : "uri",
        "value" : "http://www.wikidata.org/prop/direct/P1843"
      },
      "v" : {
        "xml:lang" : "nb",
        "type" : "literal",
        "value" : "Japansk rødfuru"
      }
    }, {
      "k" : {
        "type" : "uri",
        "value" : "http://www.wikidata.org/prop/direct/P1843"
      },
      "v" : {
        "xml:lang" : "nl",
        "type" : "literal",
        "value" : "Japanse rode den"
      }
    }, {
      "k" : {
        "type" : "uri",
        "value" : "http://www.wikidata.org/prop/direct/P1843"
      },
      "v" : {
        "xml:lang" : "pl",
        "type" : "literal",
        "value" : "Sosna gęstokwiatowa"
      }
    }, {
      "k" : {
        "type" : "uri",
        "value" : "http://www.wikidata.org/prop/direct/P1843"
      },
      "v" : {
        "xml:lang" : "ru",
        "type" : "literal",
        "value" : "Сосна густоцветная"
      }
    }, {
      "k" : {
        "type" : "uri",
        "value" : "http://www.wikidata.org/prop/direct/P2752"
      },
      "v" : {
        "type" : "literal",
        "value" : "f81f0774-0af5-4448-8ce4-6f4d46c631ca"
      }
    }, {
      "k" : {
        "type" : "uri",
        "value" : "http://www.wikidata.org/prop/direct/P3031"
      },
      "v" : {
        "type" : "literal",
        "value" : "PIUDE"
      }
    }, {
      "k" : {
        "type" : "uri",
        "value" : "http://www.wikidata.org/prop/direct/P3151"
      },
      "v" : {
        "type" : "literal",
        "value" : "135811"
      }
    }, {
      "k" : {
        "type" : "uri",
        "value" : "http://www.wikidata.org/prop/direct/P3186"
      },
      "v" : {
        "type" : "literal",
        "value" : "717407"
      }
    }, {
      "k" : {
        "type" : "uri",
        "value" : "http://www.wikidata.org/prop/direct/P3240"
      },
      "v" : {
        "type" : "literal",
        "value" : "NBNSYS0000042159"
      }
    }, {
      "k" : {
        "type" : "uri",
        "value" : "http://www.wikidata.org/prop/direct/P3591"
      },
      "v" : {
        "type" : "literal",
        "value" : "379792"
      }
    }, {
      "k" : {
        "type" : "uri",
        "value" : "http://www.wikidata.org/prop/direct/P4122"
      },
      "v" : {
        "type" : "literal",
        "value" : "Pinus_densiflora"
      }
    }, {
      "k" : {
        "type" : "uri",
        "value" : "http://www.wikidata.org/prop/direct/P4311"
      },
      "v" : {
        "type" : "literal",
        "value" : "572"
      }
    }, {
      "k" : {
        "type" : "uri",
        "value" : "http://www.wikidata.org/prop/direct-normalized/P349"
      },
      "v" : {
        "type" : "uri",
        "value" : "http://id.ndl.go.jp/auth/ndlna/00560129"
      }
    }, {
      "k" : {
        "type" : "uri",
        "value" : "http://www.wikidata.org/prop/direct-normalized/P646"
      },
      "v" : {
        "type" : "uri",
        "value" : "http://g.co/kg/m/02kdk9"
      }
    }, {
      "k" : {
        "type" : "uri",
        "value" : "http://www.wikidata.org/prop/direct-normalized/P961"
      },
      "v" : {
        "type" : "uri",
        "value" : "http://ipni.org/urn:lsid:ipni.org:names:262894-1"
      }
    }, {
      "k" : {
        "type" : "uri",
        "value" : "http://www.wikidata.org/prop/P349"
      },
      "v" : {
        "type" : "uri",
        "value" : "http://www.wikidata.org/entity/statement/Q1044186-D0797913-24AA-4A1B-81D3-DFDD5B552309"
      }
    }, {
      "k" : {
        "type" : "uri",
        "value" : "http://www.wikidata.org/prop/P373"
      },
      "v" : {
        "type" : "uri",
        "value" : "http://www.wikidata.org/entity/statement/q1044186-A769135F-C4F1-4198-9E99-B9806E72513D"
      }
    }, {
      "k" : {
        "type" : "uri",
        "value" : "http://www.wikidata.org/prop/P627"
      },
      "v" : {
        "type" : "uri",
        "value" : "http://www.wikidata.org/entity/statement/Q1044186-BCC9980F-1C0E-4FAE-9738-2ADAC3C120BE"
      }
    }, {
      "k" : {
        "type" : "uri",
        "value" : "http://www.wikidata.org/prop/P646"
      },
      "v" : {
        "type" : "uri",
        "value" : "http://www.wikidata.org/entity/statement/Q1044186-6C0329EA-BFAA-43EE-B0C1-8370358354B4"
      }
    }, {
      "k" : {
        "type" : "uri",
        "value" : "http://www.wikidata.org/prop/P685"
      },
      "v" : {
        "type" : "uri",
        "value" : "http://www.wikidata.org/entity/statement/Q1044186-D85EB82D-2204-481E-A48A-B124A2763041"
      }
    }, {
      "k" : {
        "type" : "uri",
        "value" : "http://www.wikidata.org/prop/P815"
      },
      "v" : {
        "type" : "uri",
        "value" : "http://www.wikidata.org/entity/statement/Q1044186-ACD85F4A-C223-48B2-B0AE-DE4981AA38A0"
      }
    }, {
      "k" : {
        "type" : "uri",
        "value" : "http://www.wikidata.org/prop/P830"
      },
      "v" : {
        "type" : "uri",
        "value" : "http://www.wikidata.org/entity/statement/Q1044186-cea9c70f-961a-4da1-91c9-c61aaaab068a"
      }
    }, {
      "k" : {
        "type" : "uri",
        "value" : "http://www.wikidata.org/prop/P846"
      },
      "v" : {
        "type" : "uri",
        "value" : "http://www.wikidata.org/entity/statement/Q1044186-F4230137-D3BF-483A-8CE8-98A0CF7F2D59"
      }
    }, {
      "k" : {
        "type" : "uri",
        "value" : "http://www.wikidata.org/prop/P935"
      },
      "v" : {
        "type" : "uri",
        "value" : "http://www.wikidata.org/entity/statement/Q1044186-D5519E46-483F-4B5D-B6B2-67C0B8B228A0"
      }
    }, {
      "k" : {
        "type" : "uri",
        "value" : "http://www.wikidata.org/prop/P960"
      },
      "v" : {
        "type" : "uri",
        "value" : "http://www.wikidata.org/entity/statement/Q1044186-9C2E1FF9-09F5-4365-B79C-A36DBFE2A8F0"
      }
    }, {
      "k" : {
        "type" : "uri",
        "value" : "http://www.wikidata.org/prop/P961"
      },
      "v" : {
        "type" : "uri",
        "value" : "http://www.wikidata.org/entity/statement/Q1044186-ACB927B8-1A0B-406D-86BC-99DB4747A52F"
      }
    }, {
      "k" : {
        "type" : "uri",
        "value" : "http://www.wikidata.org/prop/P1070"
      },
      "v" : {
        "type" : "uri",
        "value" : "http://www.wikidata.org/entity/statement/Q1044186-D10390BA-5F02-4804-89B4-410C96E1DEAB"
      }
    }, {
      "k" : {
        "type" : "uri",
        "value" : "http://www.wikidata.org/prop/P1421"
      },
      "v" : {
        "type" : "uri",
        "value" : "http://www.wikidata.org/entity/statement/Q1044186-DDAAEDA4-8922-4EC5-9E90-9C99388CF930"
      }
    }, {
      "k" : {
        "type" : "uri",
        "value" : "http://www.wikidata.org/prop/P1747"
      },
      "v" : {
        "type" : "uri",
        "value" : "http://www.wikidata.org/entity/statement/Q1044186-B35EB617-5ED3-40E0-984F-523BF13DC428"
      }
    }, {
      "k" : {
        "type" : "uri",
        "value" : "http://www.wikidata.org/prop/P1772"
      },
      "v" : {
        "type" : "uri",
        "value" : "http://www.wikidata.org/entity/statement/Q1044186-400C05AF-51FA-42EB-98DE-0EFEEBEBF9D0"
      }
    }, {
      "k" : {
        "type" : "uri",
        "value" : "http://www.wikidata.org/prop/P1843"
      },
      "v" : {
        "type" : "uri",
        "value" : "http://www.wikidata.org/entity/statement/Q1044186-0073CD26-5968-423D-8B24-9576F1F816B1"
      }
    }, {
      "k" : {
        "type" : "uri",
        "value" : "http://www.wikidata.org/prop/P1843"
      },
      "v" : {
        "type" : "uri",
        "value" : "http://www.wikidata.org/entity/statement/Q1044186-036A86E5-EF6B-4343-BF9A-88389A3B5872"
      }
    }, {
      "k" : {
        "type" : "uri",
        "value" : "http://www.wikidata.org/prop/P1843"
      },
      "v" : {
        "type" : "uri",
        "value" : "http://www.wikidata.org/entity/statement/Q1044186-196E7299-476D-482F-884D-75AFA6E7BE20"
      }
    }, {
      "k" : {
        "type" : "uri",
        "value" : "http://www.wikidata.org/prop/P1843"
      },
      "v" : {
        "type" : "uri",
        "value" : "http://www.wikidata.org/entity/statement/Q1044186-32D96DFE-C52A-4EF8-A79A-3E05226A00AC"
      }
    }, {
      "k" : {
        "type" : "uri",
        "value" : "http://www.wikidata.org/prop/P1843"
      },
      "v" : {
        "type" : "uri",
        "value" : "http://www.wikidata.org/entity/statement/Q1044186-39FE477C-8005-4AE3-883F-7B72662DB7A6"
      }
    }, {
      "k" : {
        "type" : "uri",
        "value" : "http://www.wikidata.org/prop/P1843"
      },
      "v" : {
        "type" : "uri",
        "value" : "http://www.wikidata.org/entity/statement/Q1044186-3A9B02DA-0AC1-47AA-B7A1-93D346A8E0EB"
      }
    }, {
      "k" : {
        "type" : "uri",
        "value" : "http://www.wikidata.org/prop/P1843"
      },
      "v" : {
        "type" : "uri",
        "value" : "http://www.wikidata.org/entity/statement/Q1044186-3FC29A28-0754-4C01-BF47-D20070EB3000"
      }
    }, {
      "k" : {
        "type" : "uri",
        "value" : "http://www.wikidata.org/prop/P1843"
      },
      "v" : {
        "type" : "uri",
        "value" : "http://www.wikidata.org/entity/statement/Q1044186-52AAA35D-D7BA-4732-8E19-1760FAE5FDFE"
      }
    }, {
      "k" : {
        "type" : "uri",
        "value" : "http://www.wikidata.org/prop/P1843"
      },
      "v" : {
        "type" : "uri",
        "value" : "http://www.wikidata.org/entity/statement/Q1044186-53ECDA73-22ED-4A9C-8610-8948B586A072"
      }
    }, {
      "k" : {
        "type" : "uri",
        "value" : "http://www.wikidata.org/prop/P1843"
      },
      "v" : {
        "type" : "uri",
        "value" : "http://www.wikidata.org/entity/statement/Q1044186-732B24BF-A9AC-4237-859A-62337FACEC2E"
      }
    }, {
      "k" : {
        "type" : "uri",
        "value" : "http://www.wikidata.org/prop/P1843"
      },
      "v" : {
        "type" : "uri",
        "value" : "http://www.wikidata.org/entity/statement/Q1044186-73CD5F94-1560-4AF0-8891-AE2ADBFB0990"
      }
    }, {
      "k" : {
        "type" : "uri",
        "value" : "http://www.wikidata.org/prop/P1843"
      },
      "v" : {
        "type" : "uri",
        "value" : "http://www.wikidata.org/entity/statement/Q1044186-9E7C7877-71F0-41E9-9CAD-4F1DE3D6568B"
      }
    }, {
      "k" : {
        "type" : "uri",
        "value" : "http://www.wikidata.org/prop/P2752"
      },
      "v" : {
        "type" : "uri",
        "value" : "http://www.wikidata.org/entity/statement/Q1044186-C7601C9A-4A36-4673-9A9A-4420E56F9252"
      }
    }, {
      "k" : {
        "type" : "uri",
        "value" : "http://www.wikidata.org/prop/P3031"
      },
      "v" : {
        "type" : "uri",
        "value" : "http://www.wikidata.org/entity/statement/Q1044186-69F03C64-796B-4D81-903D-61962BC7526C"
      }
    }, {
      "k" : {
        "type" : "uri",
        "value" : "http://www.wikidata.org/prop/P3151"
      },
      "v" : {
        "type" : "uri",
        "value" : "http://www.wikidata.org/entity/statement/Q1044186-45ED5A26-E936-42C5-B6FC-DC5D45855C76"
      }
    }, {
      "k" : {
        "type" : "uri",
        "value" : "http://www.wikidata.org/prop/P3186"
      },
      "v" : {
        "type" : "uri",
        "value" : "http://www.wikidata.org/entity/statement/Q1044186-A74283C8-845B-46B6-8B35-936ABF27428D"
      }
    }, {
      "k" : {
        "type" : "uri",
        "value" : "http://www.wikidata.org/prop/P3240"
      },
      "v" : {
        "type" : "uri",
        "value" : "http://www.wikidata.org/entity/statement/Q1044186-A58788AD-9200-4FD7-9573-D98CD20473E6"
      }
    }, {
      "k" : {
        "type" : "uri",
        "value" : "http://www.wikidata.org/prop/P3591"
      },
      "v" : {
        "type" : "uri",
        "value" : "http://www.wikidata.org/entity/statement/Q1044186-4189D7DA-8F0F-42C5-BF34-66A27714B3AE"
      }
    }, {
      "k" : {
        "type" : "uri",
        "value" : "http://www.wikidata.org/prop/P4122"
      },
      "v" : {
        "type" : "uri",
        "value" : "http://www.wikidata.org/entity/statement/Q1044186-8122D8FA-6FCA-4B00-A30E-8108D6AC1FCB"
      }
    }, {
      "k" : {
        "type" : "uri",
        "value" : "http://www.wikidata.org/prop/P4311"
      },
      "v" : {
        "type" : "uri",
        "value" : "http://www.wikidata.org/entity/statement/Q1044186-50611E88-5648-4EAC-B3BB-7F1FEE6A8F98"
      }
    }, {
      "k" : {
        "type" : "uri",
        "value" : "http://wikiba.se/ontology#identifiers"
      },
      "v" : {
        "datatype" : "http://www.w3.org/2001/XMLSchema#integer",
        "type" : "literal",
        "value" : "19"
      }
    }, {
      "k" : {
        "type" : "uri",
        "value" : "http://schema.org/version"
      },
      "v" : {
        "datatype" : "http://www.w3.org/2001/XMLSchema#integer",
        "type" : "literal",
        "value" : "623452577"
      }
    }, {
      "k" : {
        "type" : "uri",
        "value" : "http://schema.org/dateModified"
      },
      "v" : {
        "datatype" : "http://www.w3.org/2001/XMLSchema#dateTime",
        "type" : "literal",
        "value" : "2018-01-25T21:13:41Z"
      }
    }, {
      "k" : {
        "type" : "uri",
        "value" : "http://schema.org/description"
      },
      "v" : {
        "xml:lang" : "bg",
        "type" : "literal",
        "value" : "вид растение"
      }
    }, {
      "k" : {
        "type" : "uri",
        "value" : "http://schema.org/description"
      },
      "v" : {
        "xml:lang" : "bn",
        "type" : "literal",
        "value" : "উদ্ভিদের প্রজাতি"
      }
    }, {
      "k" : {
        "type" : "uri",
        "value" : "http://schema.org/description"
      },
      "v" : {
        "xml:lang" : "ca",
        "type" : "literal",
        "value" : "espècie de planta"
      }
    }, {
      "k" : {
        "type" : "uri",
        "value" : "http://schema.org/description"
      },
      "v" : {
        "xml:lang" : "en",
        "type" : "literal",
        "value" : "species of plant"
      }
    }, {
      "k" : {
        "type" : "uri",
        "value" : "http://schema.org/description"
      },
      "v" : {
        "xml:lang" : "gl",
        "type" : "literal",
        "value" : "especie de planta"
      }
    }, {
      "k" : {
        "type" : "uri",
        "value" : "http://schema.org/description"
      },
      "v" : {
        "xml:lang" : "he",
        "type" : "literal",
        "value" : "מין של צמח"
      }
    }, {
      "k" : {
        "type" : "uri",
        "value" : "http://schema.org/description"
      },
      "v" : {
        "xml:lang" : "hu",
        "type" : "literal",
        "value" : "növényfaj"
      }
    }, {
      "k" : {
        "type" : "uri",
        "value" : "http://schema.org/description"
      },
      "v" : {
        "xml:lang" : "hy",
        "type" : "literal",
        "value" : "բույսերի տեսակ"
      }
    }, {
      "k" : {
        "type" : "uri",
        "value" : "http://schema.org/description"
      },
      "v" : {
        "xml:lang" : "ro",
        "type" : "literal",
        "value" : "specie de plante"
      }
    }, {
      "k" : {
        "type" : "uri",
        "value" : "http://schema.org/description"
      },
      "v" : {
        "xml:lang" : "ru",
        "type" : "literal",
        "value" : "вид растений"
      }
    }, {
      "k" : {
        "type" : "uri",
        "value" : "http://schema.org/description"
      },
      "v" : {
        "xml:lang" : "sq",
        "type" : "literal",
        "value" : "lloj i bimëve"
      }
    }, {
      "k" : {
        "type" : "uri",
        "value" : "http://schema.org/description"
      },
      "v" : {
        "xml:lang" : "es",
        "type" : "literal",
        "value" : "especie de planta"
      }
    }, {
      "k" : {
        "type" : "uri",
        "value" : "http://schema.org/description"
      },
      "v" : {
        "xml:lang" : "ar",
        "type" : "literal",
        "value" : "نوع من السراخس الكنباثية"
      }
    }, {
      "k" : {
        "type" : "uri",
        "value" : "http://schema.org/description"
      },
      "v" : {
        "xml:lang" : "de",
        "type" : "literal",
        "value" : "Art der Gattung Kiefern (Pinus)"
      }
    }, {
      "k" : {
        "type" : "uri",
        "value" : "http://schema.org/description"
      },
      "v" : {
        "xml:lang" : "cs",
        "type" : "literal",
        "value" : "druh rostliny z rodu borovice (Pinus)"
      }
    }, {
      "k" : {
        "type" : "uri",
        "value" : "http://schema.org/description"
      },
      "v" : {
        "xml:lang" : "nl",
        "type" : "literal",
        "value" : "soort uit de sectie Pinus sect. Pinus"
      }
    }, {
      "k" : {
        "type" : "uri",
        "value" : "http://www.w3.org/2000/01/rdf-schema#label"
      },
      "v" : {
        "xml:lang" : "es",
        "type" : "literal",
        "value" : "Pinus densiflora"
      }
    }, {
      "k" : {
        "type" : "uri",
        "value" : "http://www.w3.org/2000/01/rdf-schema#label"
      },
      "v" : {
        "xml:lang" : "ko",
        "type" : "literal",
        "value" : "소나무"
      }
    }, {
      "k" : {
        "type" : "uri",
        "value" : "http://www.w3.org/2000/01/rdf-schema#label"
      },
      "v" : {
        "xml:lang" : "zh",
        "type" : "literal",
        "value" : "赤松"
      }
    }, {
      "k" : {
        "type" : "uri",
        "value" : "http://www.w3.org/2000/01/rdf-schema#label"
      },
      "v" : {
        "xml:lang" : "ar",
        "type" : "literal",
        "value" : "صنوبر كثيف الأزهار"
      }
    }, {
      "k" : {
        "type" : "uri",
        "value" : "http://www.w3.org/2000/01/rdf-schema#label"
      },
      "v" : {
        "xml:lang" : "az",
        "type" : "literal",
        "value" : "Pinus densiflora"
      }
    }, {
      "k" : {
        "type" : "uri",
        "value" : "http://www.w3.org/2000/01/rdf-schema#label"
      },
      "v" : {
        "xml:lang" : "bg",
        "type" : "literal",
        "value" : "Pinus densiflora"
      }
    }, {
      "k" : {
        "type" : "uri",
        "value" : "http://www.w3.org/2000/01/rdf-schema#label"
      },
      "v" : {
        "xml:lang" : "ceb",
        "type" : "literal",
        "value" : "Pinus densiflora"
      }
    }, {
      "k" : {
        "type" : "uri",
        "value" : "http://www.w3.org/2000/01/rdf-schema#label"
      },
      "v" : {
        "xml:lang" : "cs",
        "type" : "literal",
        "value" : "borovice hustokvětá"
      }
    }, {
      "k" : {
        "type" : "uri",
        "value" : "http://www.w3.org/2000/01/rdf-schema#label"
      },
      "v" : {
        "xml:lang" : "de",
        "type" : "literal",
        "value" : "Japanische Rotkiefer"
      }
    }, {
      "k" : {
        "type" : "uri",
        "value" : "http://www.w3.org/2000/01/rdf-schema#label"
      },
      "v" : {
        "xml:lang" : "en",
        "type" : "literal",
        "value" : "Pinus densiflora"
      }
    }, {
      "k" : {
        "type" : "uri",
        "value" : "http://www.w3.org/2000/01/rdf-schema#label"
      },
      "v" : {
        "xml:lang" : "fa",
        "type" : "literal",
        "value" : "پینس دنسیفلورا"
      }
    }, {
      "k" : {
        "type" : "uri",
        "value" : "http://www.w3.org/2000/01/rdf-schema#label"
      },
      "v" : {
        "xml:lang" : "fr",
        "type" : "literal",
        "value" : "Pin rouge du Japon"
      }
    }, {
      "k" : {
        "type" : "uri",
        "value" : "http://www.w3.org/2000/01/rdf-schema#label"
      },
      "v" : {
        "xml:lang" : "hr",
        "type" : "literal",
        "value" : "Japanski crveni bor"
      }
    }, {
      "k" : {
        "type" : "uri",
        "value" : "http://www.w3.org/2000/01/rdf-schema#label"
      },
      "v" : {
        "xml:lang" : "hu",
        "type" : "literal",
        "value" : "Japán erdeifenyő"
      }
    }, {
      "k" : {
        "type" : "uri",
        "value" : "http://www.w3.org/2000/01/rdf-schema#label"
      },
      "v" : {
        "xml:lang" : "it",
        "type" : "literal",
        "value" : "Pinus densiflora"
      }
    }, {
      "k" : {
        "type" : "uri",
        "value" : "http://www.w3.org/2000/01/rdf-schema#label"
      },
      "v" : {
        "xml:lang" : "ja",
        "type" : "literal",
        "value" : "アカマツ"
      }
    }, {
      "k" : {
        "type" : "uri",
        "value" : "http://www.w3.org/2000/01/rdf-schema#label"
      },
      "v" : {
        "xml:lang" : "koi",
        "type" : "literal",
        "value" : "Ниппонісь гӧрд пожум"
      }
    }, {
      "k" : {
        "type" : "uri",
        "value" : "http://www.w3.org/2000/01/rdf-schema#label"
      },
      "v" : {
        "xml:lang" : "la",
        "type" : "literal",
        "value" : "Pinus densiflora"
      }
    }, {
      "k" : {
        "type" : "uri",
        "value" : "http://www.w3.org/2000/01/rdf-schema#label"
      },
      "v" : {
        "xml:lang" : "mrj",
        "type" : "literal",
        "value" : "Япони якшар йӓктӹ"
      }
    }, {
      "k" : {
        "type" : "uri",
        "value" : "http://www.w3.org/2000/01/rdf-schema#label"
      },
      "v" : {
        "xml:lang" : "nb",
        "type" : "literal",
        "value" : "Japansk rødfuru"
      }
    }, {
      "k" : {
        "type" : "uri",
        "value" : "http://www.w3.org/2000/01/rdf-schema#label"
      },
      "v" : {
        "xml:lang" : "nl",
        "type" : "literal",
        "value" : "Japanse rode den"
      }
    }, {
      "k" : {
        "type" : "uri",
        "value" : "http://www.w3.org/2000/01/rdf-schema#label"
      },
      "v" : {
        "xml:lang" : "pl",
        "type" : "literal",
        "value" : "Sosna gęstokwiatowa"
      }
    }, {
      "k" : {
        "type" : "uri",
        "value" : "http://www.w3.org/2000/01/rdf-schema#label"
      },
      "v" : {
        "xml:lang" : "pt",
        "type" : "literal",
        "value" : "Pinus densiflora"
      }
    }, {
      "k" : {
        "type" : "uri",
        "value" : "http://www.w3.org/2000/01/rdf-schema#label"
      },
      "v" : {
        "xml:lang" : "ru",
        "type" : "literal",
        "value" : "Сосна густоцветная"
      }
    }, {
      "k" : {
        "type" : "uri",
        "value" : "http://www.w3.org/2000/01/rdf-schema#label"
      },
      "v" : {
        "xml:lang" : "sv",
        "type" : "literal",
        "value" : "Pinus densiflora"
      }
    }, {
      "k" : {
        "type" : "uri",
        "value" : "http://www.w3.org/2000/01/rdf-schema#label"
      },
      "v" : {
        "xml:lang" : "udm",
        "type" : "literal",
        "value" : "Япониысь горд пужым"
      }
    }, {
      "k" : {
        "type" : "uri",
        "value" : "http://www.w3.org/2000/01/rdf-schema#label"
      },
      "v" : {
        "xml:lang" : "uk",
        "type" : "literal",
        "value" : "Pinus densiflora"
      }
    }, {
      "k" : {
        "type" : "uri",
        "value" : "http://www.w3.org/2000/01/rdf-schema#label"
      },
      "v" : {
        "xml:lang" : "vi",
        "type" : "literal",
        "value" : "Pinus densiflora"
      }
    }, {
      "k" : {
        "type" : "uri",
        "value" : "http://www.w3.org/2000/01/rdf-schema#label"
      },
      "v" : {
        "xml:lang" : "war",
        "type" : "literal",
        "value" : "Pinus densiflora"
      }
    }, {
      "k" : {
        "type" : "uri",
        "value" : "http://www.w3.org/2000/01/rdf-schema#label"
      },
      "v" : {
        "xml:lang" : "zh-hans",
        "type" : "literal",
        "value" : "赤松"
      }
    }, {
      "k" : {
        "type" : "uri",
        "value" : "http://www.w3.org/2000/01/rdf-schema#label"
      },
      "v" : {
        "xml:lang" : "zh-hant",
        "type" : "literal",
        "value" : "赤松"
      }
    }, {
      "k" : {
        "type" : "uri",
        "value" : "http://www.w3.org/2000/01/rdf-schema#label"
      },
      "v" : {
        "xml:lang" : "zh-hk",
        "type" : "literal",
        "value" : "赤松"
      }
    }, {
      "k" : {
        "type" : "uri",
        "value" : "http://www.w3.org/2004/02/skos/core#altLabel"
      },
      "v" : {
        "xml:lang" : "de",
        "type" : "literal",
        "value" : "Pinus densiflora"
      }
    }, {
      "k" : {
        "type" : "uri",
        "value" : "http://www.w3.org/2004/02/skos/core#altLabel"
      },
      "v" : {
        "xml:lang" : "zh",
        "type" : "literal",
        "value" : "千头赤松"
      }
    }, {
      "k" : {
        "type" : "uri",
        "value" : "http://www.w3.org/2004/02/skos/core#altLabel"
      },
      "v" : {
        "xml:lang" : "de",
        "type" : "literal",
        "value" : "Japanische Rot-Kiefer"
      }
    }, {
      "k" : {
        "type" : "uri",
        "value" : "http://www.w3.org/2004/02/skos/core#altLabel"
      },
      "v" : {
        "xml:lang" : "en",
        "type" : "literal",
        "value" : "Japanese Red Pine"
      }
    }, {
      "k" : {
        "type" : "uri",
        "value" : "http://www.w3.org/2004/02/skos/core#altLabel"
      },
      "v" : {
        "xml:lang" : "es",
        "type" : "literal",
        "value" : "Pino rojo japones"
      }
    }, {
      "k" : {
        "type" : "uri",
        "value" : "http://www.w3.org/2004/02/skos/core#altLabel"
      },
      "v" : {
        "xml:lang" : "es",
        "type" : "literal",
        "value" : "Pino rojo japonés"
      }
    }, {
      "k" : {
        "type" : "uri",
        "value" : "http://www.w3.org/2004/02/skos/core#altLabel"
      },
      "v" : {
        "xml:lang" : "fr",
        "type" : "literal",
        "value" : "Pinus densiflora"
      }
    }, {
      "k" : {
        "type" : "uri",
        "value" : "http://www.w3.org/2004/02/skos/core#altLabel"
      },
      "v" : {
        "xml:lang" : "hu",
        "type" : "literal",
        "value" : "Pinus densiflora"
      }
    }, {
      "k" : {
        "type" : "uri",
        "value" : "http://www.w3.org/2004/02/skos/core#altLabel"
      },
      "v" : {
        "xml:lang" : "hu",
        "type" : "literal",
        "value" : "Vöröskérgű fenyő"
      }
    }, {
      "k" : {
        "type" : "uri",
        "value" : "http://www.w3.org/2004/02/skos/core#altLabel"
      },
      "v" : {
        "xml:lang" : "ja",
        "type" : "literal",
        "value" : "メマツ"
      }
    }, {
      "k" : {
        "type" : "uri",
        "value" : "http://www.w3.org/2004/02/skos/core#altLabel"
      },
      "v" : {
        "xml:lang" : "ja",
        "type" : "literal",
        "value" : "雌松"
      }
    }, {
      "k" : {
        "type" : "uri",
        "value" : "http://www.w3.org/2004/02/skos/core#altLabel"
      },
      "v" : {
        "xml:lang" : "ko",
        "type" : "literal",
        "value" : "금강송"
      }
    }, {
      "k" : {
        "type" : "uri",
        "value" : "http://www.w3.org/2004/02/skos/core#altLabel"
      },
      "v" : {
        "xml:lang" : "ko",
        "type" : "literal",
        "value" : "적송"
      }
    }, {
      "k" : {
        "type" : "uri",
        "value" : "http://www.w3.org/2004/02/skos/core#altLabel"
      },
      "v" : {
        "xml:lang" : "koi",
        "type" : "literal",
        "value" : "Pinus densiflora"
      }
    }, {
      "k" : {
        "type" : "uri",
        "value" : "http://www.w3.org/2004/02/skos/core#altLabel"
      },
      "v" : {
        "xml:lang" : "mrj",
        "type" : "literal",
        "value" : "Pinus densiflora"
      }
    }, {
      "k" : {
        "type" : "uri",
        "value" : "http://www.w3.org/2004/02/skos/core#altLabel"
      },
      "v" : {
        "xml:lang" : "nb",
        "type" : "literal",
        "value" : "Pinus densiflora"
      }
    }, {
      "k" : {
        "type" : "uri",
        "value" : "http://www.w3.org/2004/02/skos/core#altLabel"
      },
      "v" : {
        "xml:lang" : "nb",
        "type" : "literal",
        "value" : "Pinus leucodermis"
      }
    }, {
      "k" : {
        "type" : "uri",
        "value" : "http://www.w3.org/2004/02/skos/core#altLabel"
      },
      "v" : {
        "xml:lang" : "nl",
        "type" : "literal",
        "value" : "Pinus densiflora"
      }
    }, {
      "k" : {
        "type" : "uri",
        "value" : "http://www.w3.org/2004/02/skos/core#altLabel"
      },
      "v" : {
        "xml:lang" : "pl",
        "type" : "literal",
        "value" : "Pinus densiflora"
      }
    }, {
      "k" : {
        "type" : "uri",
        "value" : "http://www.w3.org/2004/02/skos/core#altLabel"
      },
      "v" : {
        "xml:lang" : "ru",
        "type" : "literal",
        "value" : "Pinus densiflora"
      }
    }, {
      "k" : {
        "type" : "uri",
        "value" : "http://www.w3.org/2004/02/skos/core#altLabel"
      },
      "v" : {
        "xml:lang" : "udm",
        "type" : "literal",
        "value" : "Pinus densiflora"
      }
    }, {
      "k" : {
        "type" : "uri",
        "value" : "http://wikiba.se/ontology#statements"
      },
      "v" : {
        "datatype" : "http://www.w3.org/2001/XMLSchema#integer",
        "type" : "literal",
        "value" : "41"
      }
    }, {
      "k" : {
        "type" : "uri",
        "value" : "http://wikiba.se/ontology#sitelinks"
      },
      "v" : {
        "datatype" : "http://www.w3.org/2001/XMLSchema#integer",
        "type" : "literal",
        "value" : "31"
      }
    }, {
      "k" : {
        "type" : "uri",
        "value" : "http://www.wikidata.org/prop/direct/P18"
      },
      "v" : {
        "type" : "uri",
        "value" : "http://commons.wikimedia.org/wiki/Special:FilePath/Pinus%20syluestriformis%20%28Takenouchi%29T.Wang%20ex%20Cheng.JPG"
      }
    }, {
      "k" : {
        "type" : "uri",
        "value" : "http://www.wikidata.org/prop/direct/P31"
      },
      "v" : {
        "type" : "uri",
        "value" : "http://www.wikidata.org/entity/Q16521"
      }
    }, {
      "k" : {
        "type" : "uri",
        "value" : "http://www.wikidata.org/prop/direct/P105"
      },
      "v" : {
        "type" : "uri",
        "value" : "http://www.wikidata.org/entity/Q7432"
      }
    }, {
      "k" : {
        "type" : "uri",
        "value" : "http://www.wikidata.org/prop/direct/P141"
      },
      "v" : {
        "type" : "uri",
        "value" : "http://www.wikidata.org/entity/Q211005"
      }
    }, {
      "k" : {
        "type" : "uri",
        "value" : "http://www.wikidata.org/prop/direct/P171"
      },
      "v" : {
        "type" : "uri",
        "value" : "http://www.wikidata.org/entity/Q14965389"
      }
    }, {
      "k" : {
        "type" : "uri",
        "value" : "http://www.wikidata.org/prop/direct/P225"
      },
      "v" : {
        "type" : "literal",
        "value" : "Pinus densiflora"
      }
    }, {
      "k" : {
        "type" : "uri",
        "value" : "http://www.wikidata.org/prop/P18"
      },
      "v" : {
        "type" : "uri",
        "value" : "http://www.wikidata.org/entity/statement/q1044186-CF860414-2CC9-4D86-B823-CEC49E083A34"
      }
    }, {
      "k" : {
        "type" : "uri",
        "value" : "http://www.wikidata.org/prop/P31"
      },
      "v" : {
        "type" : "uri",
        "value" : "http://www.wikidata.org/entity/statement/Q1044186-8C3DE30D-BC8C-4D47-8D16-0EAF8D20878C"
      }
    }, {
      "k" : {
        "type" : "uri",
        "value" : "http://www.wikidata.org/prop/P105"
      },
      "v" : {
        "type" : "uri",
        "value" : "http://www.wikidata.org/entity/statement/q1044186-8833C8AA-3D93-4DC7-9FF9-41E07E4D9BB8"
      }
    }, {
      "k" : {
        "type" : "uri",
        "value" : "http://www.wikidata.org/prop/P141"
      },
      "v" : {
        "type" : "uri",
        "value" : "http://www.wikidata.org/entity/statement/q1044186-6791B5AE-B5E8-463D-8EC3-A8E6CCC98C6C"
      }
    }, {
      "k" : {
        "type" : "uri",
        "value" : "http://www.wikidata.org/prop/P171"
      },
      "v" : {
        "type" : "uri",
        "value" : "http://www.wikidata.org/entity/statement/Q1044186-5a5991a1-44a8-d8a7-b163-b577866448a8"
      }
    }, {
      "k" : {
        "type" : "uri",
        "value" : "http://www.wikidata.org/prop/P225"
      },
      "v" : {
        "type" : "uri",
        "value" : "http://www.wikidata.org/entity/statement/q1044186-6947D009-63AE-4C5F-8F3A-D3E5ABBFB70C"
      }
    }, {
      "k" : {
        "type" : "uri",
        "value" : "http://www.wikidata.org/prop/direct/P349"
      },
      "v" : {
        "type" : "literal",
        "value" : "00560129"
      }
    }, {
      "k" : {
        "type" : "uri",
        "value" : "http://www.wikidata.org/prop/direct/P373"
      },
      "v" : {
        "type" : "literal",
        "value" : "Pinus densiflora"
      }
    }, {
      "k" : {
        "type" : "uri",
        "value" : "http://www.wikidata.org/prop/direct/P627"
      },
      "v" : {
        "type" : "literal",
        "value" : "42355"
      }
    }, {
      "k" : {
        "type" : "uri",
        "value" : "http://www.wikidata.org/prop/direct/P646"
      },
      "v" : {
        "type" : "literal",
        "value" : "/m/02kdk9"
      }
    }, {
      "k" : {
        "type" : "uri",
        "value" : "http://www.wikidata.org/prop/direct/P685"
      },
      "v" : {
        "type" : "literal",
        "value" : "77912"
      }
    }, {
      "k" : {
        "type" : "uri",
        "value" : "http://www.wikidata.org/prop/direct/P815"
      },
      "v" : {
        "type" : "literal",
        "value" : "822552"
      }
    }, {
      "k" : {
        "type" : "uri",
        "value" : "http://www.wikidata.org/prop/direct/P830"
      },
      "v" : {
        "type" : "literal",
        "value" : "1033597"
      }
    }, {
      "k" : {
        "type" : "uri",
        "value" : "http://www.wikidata.org/prop/direct/P846"
      },
      "v" : {
        "type" : "literal",
        "value" : "5285104"
      }
    }, {
      "k" : {
        "type" : "uri",
        "value" : "http://www.wikidata.org/prop/direct/P935"
      },
      "v" : {
        "type" : "literal",
        "value" : "Pinus densiflora"
      }
    }, {
      "k" : {
        "type" : "uri",
        "value" : "http://www.wikidata.org/prop/direct/P960"
      },
      "v" : {
        "type" : "literal",
        "value" : "24900108"
      }
    }, {
      "k" : {
        "type" : "uri",
        "value" : "http://www.wikidata.org/prop/direct/P961"
      },
      "v" : {
        "type" : "literal",
        "value" : "262894-1"
      }
    }, {
      "k" : {
        "type" : "uri",
        "value" : "http://www.wikidata.org/prop/direct/P1070"
      },
      "v" : {
        "type" : "literal",
        "value" : "kew-2561880"
      }
    }, {
      "k" : {
        "type" : "uri",
        "value" : "http://www.wikidata.org/prop/direct/P1421"
      },
      "v" : {
        "type" : "uri",
        "value" : "https://npgsweb.ars-grin.gov/gringlobal/taxonomydetail.aspx?id=28441"
      }
    }, {
      "k" : {
        "type" : "uri",
        "value" : "http://www.wikidata.org/prop/direct/P1747"
      },
      "v" : {
        "type" : "literal",
        "value" : "200005331"
      }
    } ]
  }
}